mllearn_lyt/__init__.py
mllearn_lyt/KNN/__init__.py
mllearn_lyt/KNN/_kd_tree.py
mllearn_lyt-0.0.2.1.dist-info/LICENSE
mllearn_lyt-0.0.2.1.dist-info/METADATA
mllearn_lyt-0.0.2.1.dist-info/WHEEL
mllearn_lyt-0.0.2.1.dist-info/top_level.txt
mllearn_lyt-0.0.2.1.dist-info/RECORD
