Metadata-Version: 2.1
Name: mllearn-lyt
Version: 0.0.2.1
Summary: Machine Learning in Python
Home-page: http://lyt0628.icu
Download-URL: http://github.com//LYT0628/mllearn
Author: lyt0628
Author-email: lyt0628 <lyt.0628@qq.com>
Project-URL: Homepage, https://github.com/LYT0628/mllearn
Project-URL: Issues, https://github.com/LYT0628/mllearn/issues
Classifier: Programming Language :: Python :: 3
Classifier: License :: OSI Approved :: MIT License
Classifier: Operating System :: OS Independent
Requires-Python: >=3.8
License-File: LICENSE
